project_utils/__init__.py
project_utils/io.py
project_utils/time.py
project_utils/collection/__init__.py
project_utils/collection/list_util.py
project_utils/conf/__init__.py
project_utils/conf/base_config.py
project_utils/conf/template.py
project_utils/conf/addr_config/__init__.py
project_utils/conf/addr_config/base_config.py
project_utils/conf/addr_config/hbase_config.py
project_utils/conf/addr_config/kafka_config.py
project_utils/conf/addr_config/mysql_config.py
project_utils/conf/addr_config/redis_config.py
project_utils/conf/path_config/__init__.py
project_utils/conf/path_config/path_config.py
project_utils/db/__init__.py
project_utils/db/mysql/__init__.py
project_utils/db/mysql/_collection.py
project_utils/db/mysql/_pool.py
project_utils/db/mysql/_result.py
project_utils/db/mysql/_types.py
project_utils/exception/__init__.py
project_utils/exception/collection_exception.py
project_utils/exception/config_exception.py
project_utils/exception/my_base_exception.py
project_utils/exception/db_exception/__init__.py
project_utils/exception/db_exception/mysql_exception.py
project_utils/exception/web_exception/__init__.py
project_utils/exception/web_exception/django_exception/__init__.py
project_utils/exception/web_exception/django_exception/model_exception.py
project_utils/exception/web_exception/django_exception/view_exception/__init__.py
project_utils/exception/web_exception/django_exception/view_exception/response_exception.py
project_utils/os/__init__.py
project_utils/os/dir.py
project_utils/scripts/__init__.py
project_utils/scripts/_base.py
project_utils/web/__init__.py
project_utils/web/aiohttp/__init__.py
project_utils/web/django/__init__.py
project_utils/web/django/utils.py
project_utils/web/django/celery/__init__.py
project_utils/web/django/celery/create_app.py
project_utils/web/django/celery/_conf/__init__.py
project_utils/web/django/celery/_conf/_celery_config.py
project_utils/web/django/conf/__init__.py
project_utils/web/django/conf/_django_config.py
project_utils_flask-1.0.1.dist-info/LICENSE
project_utils_flask-1.0.1.dist-info/METADATA
project_utils_flask-1.0.1.dist-info/WHEEL
project_utils_flask-1.0.1.dist-info/top_level.txt
project_utils_flask-1.0.1.dist-info/RECORD
