Metadata-Version: 2.1
Name: project-utils-flask
Version: 1.0.1
Summary: python project_utils tools
Home-page: https://gitee.com/mylx2014/project-utils.git
Author: mylx2014
Author-email: mylx2014@163.com
License: MIT
Keywords: python,utils,project utils,aiofiles,flask
Classifier: Programming Language :: Python :: 3.8
License-File: LICENSE
Requires-Dist: asyncio
Requires-Dist: loguru
Requires-Dist: dbutils
Requires-Dist: pymysql
